{
  "bug_id": "64669",
  "issue_url": "https://github.com/llvm/llvm-project/issues/64669",
  "bug_type": "miscompilation",
  "base_commit": "f44beecb78d25dca27de74823e1d958c8bd57d31",
  "knowledge_cutoff": "2023-08-14T07:09:03Z",
  "lit_test_dir": [
    "llvm/test/Transforms/InstCombine"
  ],
  "hints": {
    "fix_commit": "c15ccfb24afa67d3c3f54e52cc1d1afa564715ed",
    "components": [
      "InstCombine"
    ],
    "bug_location_lineno": {
      "llvm/lib/Transforms/InstCombine/InstructionCombining.cpp": [
        [
          908,
          914
        ]
      ]
    },
    "bug_location_funcname": {
      "llvm/lib/Transforms/InstCombine/InstructionCombining.cpp": [
        "InstCombinerImpl::foldBinOpOfSelectAndCastOfSelectCondition"
      ]
    }
  },
  "patch": "commit c15ccfb24afa67d3c3f54e52cc1d1afa564715ed\nAuthor: Nikita Popov <npopov@redhat.com>\nDate:   Mon Aug 14 17:39:48 2023 +0200\n\n    [InstCombine] Fix select + cast fold with constant expression (PR64669)\n    \n    The zext constant expression was detected by the fold, but then\n    handled as a sext. Use ZExtOperator instead of ZExtInst to handle\n    constant expressions.\n    \n    Fixes https://github.com/llvm/llvm-project/issues/64669.\n\ndiff --git a/llvm/lib/Transforms/InstCombine/InstructionCombining.cpp b/llvm/lib/Transforms/InstCombine/InstructionCombining.cpp\nindex 01ca0894ac35..2722160e72c1 100644\n--- a/llvm/lib/Transforms/InstCombine/InstructionCombining.cpp\n+++ b/llvm/lib/Transforms/InstCombine/InstructionCombining.cpp\n@@ -908,7 +908,7 @@ InstCombinerImpl::foldBinOpOfSelectAndCastOfSelectCondition(BinaryOperator &I) {\n \n   auto NewFoldedConst = [&](bool IsTrueArm, Value *V) {\n     bool IsCastOpRHS = (CastOp == RHS);\n-    bool IsZExt = isa<ZExtInst>(CastOp);\n+    bool IsZExt = isa<ZExtOperator>(CastOp);\n     Constant *C;\n \n     if (IsTrueArm) {\n",
  "tests": [],
  "issue": {
    "title": "Wrong code at -O1 and above on x86_64-linux_gnu since f12a556",
    "body": "This is a recent regression. Clang at -O1 and above produced the wrong code.\r\n\r\nBisected to f12a5561b2cbfae384c9a31293938ee2acea79fd, which was committed by @antoniofrighetto \r\n\r\nCompiler explorer: https://godbolt.org/z/q4fsW5Ge7\r\n\r\n```console\r\n% cat a.c \r\nint printf(const char *, ...);\r\nlong a, e;\r\nint b[72];\r\nint c, g, h;\r\nchar d;\r\nint main() {\r\n  int *f = &b[25], *i = &c;\r\n  d = f != i;\r\n  e = a * d;\r\n  *f = e + d;\r\n  printf(\"%d\\n\", b[25]);\r\n}\r\n%\r\n% clang-f12a556 -O0 a.c && ./a.out\r\n1\r\n% clang-f12a556 -O1 a.c && ./a.out\r\n-1\r\n% clang-f12a556 -O2 a.c && ./a.out\r\n-1\r\n%\r\n```",
    "author": "shao-hua-li",
    "labels": [
      "miscompilation",
      "release:backport",
      "release:merged",
      "llvm:instcombine"
    ],
    "comments": [
      {
        "author": "nikic",
        "body": "Reduced:\r\n```\r\n@b = external global [72 x i32]\r\n@c = external global i32\r\n\r\ndefine i64 @test(i64 %a) {\r\n  %mul = select i1 icmp ne (ptr getelementptr inbounds ([72 x i32], ptr @b, i64 0, i64 25), ptr @c), i64 %a, i64 0\r\n  %conv3 = zext i1 icmp ne (ptr getelementptr inbounds ([72 x i32], ptr @b, i64 0, i64 25), ptr @c) to i64\r\n  %add = add nsw i64 %mul, %conv3\r\n  ret i64 %add\r\n}\r\n```\r\nFolds to:\r\n```\r\ndefine i64 @test(i64 %a) {\r\n  %1 = add i64 %a, -1\r\n  %add = select i1 icmp ne (ptr getelementptr inbounds ([72 x i32], ptr @b, i64 0, i64 25), ptr @c), i64 %1, i64 0\r\n  ret i64 %add\r\n}\r\n```\r\nThe -1 should be 1.\r\n\r\nThis is due to https://github.com/llvm/llvm-project/blob/d7fcb5b6b5280dc61d5afe0920bb78a82cfe2f27/llvm/lib/Transforms/InstCombine/InstructionCombining.cpp#L911 Constant expressions strike again!\r\n"
      },
      {
        "author": "nikic",
        "body": "Looks like this is also on the release branch.\r\n\r\n/cherry-pick c15ccfb24afa67d3c3f54e52cc1d1afa564715ed"
      }
    ]
  },
  "properties": {
    "is_single_file_fix": true,
    "is_single_func_fix": true
  }
}