{
  "bug_id": "70547",
  "issue_url": "https://github.com/llvm/llvm-project/issues/70547",
  "bug_type": "miscompilation",
  "base_commit": "29fd9bab2c9d04b90def77151961c02c940b15bb",
  "knowledge_cutoff": "2023-10-28T10:18:25Z",
  "lit_test_dir": [
    "llvm/test/Transforms/DeadStoreElimination"
  ],
  "hints": {
    "fix_commit": "fd95f398c7623ff4a62e5001b4cde21c5b9eb111",
    "components": [
      "AliasAnalysis",
      "CaptureTracking",
      "DeadStoreElimination"
    ],
    "bug_location_lineno": {
      "llvm/include/llvm/Analysis/AliasAnalysis.h": [
        [
          184,
          195
        ]
      ],
      "llvm/include/llvm/Analysis/CaptureTracking.h": [
        [
          25,
          31
        ],
        [
          45,
          57
        ],
        [
          80,
          90
        ]
      ],
      "llvm/lib/Analysis/BasicAliasAnalysis.cpp": [
        [
          208,
          214
        ]
      ],
      "llvm/lib/Analysis/CaptureTracking.cpp": [
        [
          16,
          22
        ],
        [
          74,
          83
        ],
        [
          88,
          104
        ],
        [
          166,
          174
        ],
        [
          180,
          188
        ],
        [
          194,
          201
        ],
        [
          217,
          233
        ],
        [
          239,
          245
        ],
        [
          283,
          297
        ]
      ],
      "llvm/lib/Transforms/Scalar/DeadStoreElimination.cpp": [
        [
          38,
          46
        ],
        [
          842,
          850
        ],
        [
          864,
          873
        ],
        [
          897,
          904
        ],
        [
          1075,
          1081
        ],
        [
          1094,
          1100
        ],
        [
          2065,
          2076
        ],
        [
          2251,
          2260
        ]
      ]
    },
    "bug_location_funcname": {
      "llvm/include/llvm/Analysis/AliasAnalysis.h": [
        "EarliestEscapeInfo"
      ],
      "llvm/lib/Analysis/BasicAliasAnalysis.cpp": [
        "EarliestEscapeInfo::isNotCapturedBeforeOrAt"
      ],
      "llvm/lib/Analysis/CaptureTracking.cpp": [
        "EarliestCaptures",
        "SimpleCaptureTracker",
        "captured",
        "llvm::FindEarliestCapture",
        "llvm::PointerMayBeCapturedBefore",
        "tooManyUses"
      ],
      "llvm/lib/Transforms/Scalar/DeadStoreElimination.cpp": [
        "DSEPass::run",
        "DSEState",
        "eliminateDeadStores",
        "getLocForWrite",
        "isInvisibleToCallerAfterRet",
        "isInvisibleToCallerOnUnwind",
        "strengthenLocationSize"
      ]
    }
  },
  "patch": "commit fd95f398c7623ff4a62e5001b4cde21c5b9eb111\nAuthor: Florian Hahn <flo@fhahn.com>\nDate:   Thu Nov 2 20:23:38 2023 +0000\n\n    Revert \"[CaptureTracking] Ignore ephemeral values when determining po\u2026 (#71066)\n    \n    Unfortunately the commit (D123162) introduced a mis-compile\n    (https://github.com/llvm/llvm-project/issues/70547), which wasn't fixed\n    by the alternative fix (c0de28b92e98acbeb73)\n    \n    I think as long as the call considered as ephemeral is not removed, we\n    need to be conservative. To address the correctness issue quickly, I\n    think we should revert the patch (as this patch does, it doens't revert\n    cleanly)\n    \n    This reverts commit 17fdaccccfad9b143e4aadbcdda7f645de127153.\n    \n    Fixes https://github.com/llvm/llvm-project/issues/70547\n\ndiff --git a/llvm/include/llvm/Analysis/AliasAnalysis.h b/llvm/include/llvm/Analysis/AliasAnalysis.h\nindex 9bcf97137875..0d0e94a89976 100644\n--- a/llvm/include/llvm/Analysis/AliasAnalysis.h\n+++ b/llvm/include/llvm/Analysis/AliasAnalysis.h\n@@ -184,12 +184,9 @@ class EarliestEscapeInfo final : public CaptureInfo {\n   /// This is used for cache invalidation purposes.\n   DenseMap<Instruction *, TinyPtrVector<const Value *>> Inst2Obj;\n \n-  const SmallPtrSetImpl<const Value *> *EphValues;\n-\n public:\n-  EarliestEscapeInfo(DominatorTree &DT, const LoopInfo *LI = nullptr,\n-                     const SmallPtrSetImpl<const Value *> *EphValues = nullptr)\n-      : DT(DT), LI(LI), EphValues(EphValues) {}\n+  EarliestEscapeInfo(DominatorTree &DT, const LoopInfo *LI = nullptr)\n+      : DT(DT), LI(LI) {}\n \n   bool isNotCapturedBeforeOrAt(const Value *Object,\n                                const Instruction *I) override;\ndiff --git a/llvm/include/llvm/Analysis/CaptureTracking.h b/llvm/include/llvm/Analysis/CaptureTracking.h\nindex 6589c2b86363..2825399e2cc4 100644\n--- a/llvm/include/llvm/Analysis/CaptureTracking.h\n+++ b/llvm/include/llvm/Analysis/CaptureTracking.h\n@@ -25,7 +25,6 @@ namespace llvm {\n   class DominatorTree;\n   class LoopInfo;\n   class Function;\n-  template <typename T> class SmallPtrSetImpl;\n \n   /// getDefaultMaxUsesToExploreForCaptureTracking - Return default value of\n   /// the maximal number of uses to explore before giving up. It is used by\n@@ -45,13 +44,6 @@ namespace llvm {\n   bool PointerMayBeCaptured(const Value *V, bool ReturnCaptures,\n                             bool StoreCaptures, unsigned MaxUsesToExplore = 0);\n \n-  /// Variant of the above function which accepts a set of Values that are\n-  /// ephemeral and cannot cause pointers to escape.\n-  bool PointerMayBeCaptured(const Value *V, bool ReturnCaptures,\n-                            bool StoreCaptures,\n-                            const SmallPtrSetImpl<const Value *> &EphValues,\n-                            unsigned MaxUsesToExplore = 0);\n-\n   /// PointerMayBeCapturedBefore - Return true if this pointer value may be\n   /// captured by the enclosing function (which is required to exist). If a\n   /// DominatorTree is provided, only captures which happen before the given\n@@ -80,11 +72,10 @@ namespace llvm {\n   // nullptr is returned. Note that the caller of the function has to ensure\n   // that the instruction the result value is compared against is not in a\n   // cycle.\n-  Instruction *\n-  FindEarliestCapture(const Value *V, Function &F, bool ReturnCaptures,\n-                      bool StoreCaptures, const DominatorTree &DT,\n-                      const SmallPtrSetImpl<const Value *> *EphValues = nullptr,\n-                      unsigned MaxUsesToExplore = 0);\n+  Instruction *FindEarliestCapture(const Value *V, Function &F,\n+                                   bool ReturnCaptures, bool StoreCaptures,\n+                                   const DominatorTree &DT,\n+                                   unsigned MaxUsesToExplore = 0);\n \n   /// This callback is used in conjunction with PointerMayBeCaptured. In\n   /// addition to the interface here, you'll need to provide your own getters\ndiff --git a/llvm/lib/Analysis/BasicAliasAnalysis.cpp b/llvm/lib/Analysis/BasicAliasAnalysis.cpp\nindex f70b39b4f51a..a369ebe82320 100644\n--- a/llvm/lib/Analysis/BasicAliasAnalysis.cpp\n+++ b/llvm/lib/Analysis/BasicAliasAnalysis.cpp\n@@ -208,7 +208,7 @@ bool EarliestEscapeInfo::isNotCapturedBeforeOrAt(const Value *Object,\n   if (Iter.second) {\n     Instruction *EarliestCapture = FindEarliestCapture(\n         Object, *const_cast<Function *>(I->getFunction()),\n-        /*ReturnCaptures=*/false, /*StoreCaptures=*/true, DT, EphValues);\n+        /*ReturnCaptures=*/false, /*StoreCaptures=*/true, DT);\n     if (EarliestCapture) {\n       auto Ins = Inst2Obj.insert({EarliestCapture, {}});\n       Ins.first->second.push_back(Object);\ndiff --git a/llvm/lib/Analysis/CaptureTracking.cpp b/llvm/lib/Analysis/CaptureTracking.cpp\nindex 2b9362054834..0d6d30923bb5 100644\n--- a/llvm/lib/Analysis/CaptureTracking.cpp\n+++ b/llvm/lib/Analysis/CaptureTracking.cpp\n@@ -16,7 +16,6 @@\n //===----------------------------------------------------------------------===//\n \n #include \"llvm/Analysis/CaptureTracking.h\"\n-#include \"llvm/ADT/SmallPtrSet.h\"\n #include \"llvm/ADT/SmallSet.h\"\n #include \"llvm/ADT/SmallVector.h\"\n #include \"llvm/ADT/Statistic.h\"\n@@ -74,10 +73,8 @@ bool CaptureTracker::isDereferenceableOrNull(Value *O, const DataLayout &DL) {\n \n namespace {\n   struct SimpleCaptureTracker : public CaptureTracker {\n-    explicit SimpleCaptureTracker(\n-\n-        const SmallPtrSetImpl<const Value *> &EphValues, bool ReturnCaptures)\n-        : EphValues(EphValues), ReturnCaptures(ReturnCaptures) {}\n+    explicit SimpleCaptureTracker(bool ReturnCaptures)\n+        : ReturnCaptures(ReturnCaptures) {}\n \n     void tooManyUses() override {\n       LLVM_DEBUG(dbgs() << \"Captured due to too many uses\\n\");\n@@ -88,17 +85,12 @@ namespace {\n       if (isa<ReturnInst>(U->getUser()) && !ReturnCaptures)\n         return false;\n \n-      if (EphValues.contains(U->getUser()))\n-        return false;\n-\n       LLVM_DEBUG(dbgs() << \"Captured by: \" << *U->getUser() << \"\\n\");\n \n       Captured = true;\n       return true;\n     }\n \n-    const SmallPtrSetImpl<const Value *> &EphValues;\n-\n     bool ReturnCaptures;\n \n     bool Captured = false;\n@@ -166,9 +158,8 @@ namespace {\n   // escape are not in a cycle.\n   struct EarliestCaptures : public CaptureTracker {\n \n-    EarliestCaptures(bool ReturnCaptures, Function &F, const DominatorTree &DT,\n-                     const SmallPtrSetImpl<const Value *> *EphValues)\n-        : EphValues(EphValues), DT(DT), ReturnCaptures(ReturnCaptures), F(F) {}\n+    EarliestCaptures(bool ReturnCaptures, Function &F, const DominatorTree &DT)\n+        : DT(DT), ReturnCaptures(ReturnCaptures), F(F) {}\n \n     void tooManyUses() override {\n       Captured = true;\n@@ -180,9 +171,6 @@ namespace {\n       if (isa<ReturnInst>(I) && !ReturnCaptures)\n         return false;\n \n-      if (EphValues && EphValues->contains(I))\n-        return false;\n-\n       if (!EarliestCapture)\n         EarliestCapture = I;\n       else\n@@ -194,8 +182,6 @@ namespace {\n       return false;\n     }\n \n-    const SmallPtrSetImpl<const Value *> *EphValues;\n-\n     Instruction *EarliestCapture = nullptr;\n \n     const DominatorTree &DT;\n@@ -217,17 +203,6 @@ namespace {\n /// counts as capturing it or not.\n bool llvm::PointerMayBeCaptured(const Value *V, bool ReturnCaptures,\n                                 bool StoreCaptures, unsigned MaxUsesToExplore) {\n-  SmallPtrSet<const Value *, 1> Empty;\n-  return PointerMayBeCaptured(V, ReturnCaptures, StoreCaptures, Empty,\n-                              MaxUsesToExplore);\n-}\n-\n-/// Variant of the above function which accepts a set of Values that are\n-/// ephemeral and cannot cause pointers to escape.\n-bool llvm::PointerMayBeCaptured(const Value *V, bool ReturnCaptures,\n-                                bool StoreCaptures,\n-                                const SmallPtrSetImpl<const Value *> &EphValues,\n-                                unsigned MaxUsesToExplore) {\n   assert(!isa<GlobalValue>(V) &&\n          \"It doesn't make sense to ask whether a global is captured.\");\n \n@@ -239,7 +214,7 @@ bool llvm::PointerMayBeCaptured(const Value *V, bool ReturnCaptures,\n \n   LLVM_DEBUG(dbgs() << \"Captured?: \" << *V << \" = \");\n \n-  SimpleCaptureTracker SCT(EphValues, ReturnCaptures);\n+  SimpleCaptureTracker SCT(ReturnCaptures);\n   PointerMayBeCaptured(V, &SCT, MaxUsesToExplore);\n   if (SCT.Captured)\n     ++NumCaptured;\n@@ -283,15 +258,14 @@ bool llvm::PointerMayBeCapturedBefore(const Value *V, bool ReturnCaptures,\n   return CB.Captured;\n }\n \n-Instruction *\n-llvm::FindEarliestCapture(const Value *V, Function &F, bool ReturnCaptures,\n-                          bool StoreCaptures, const DominatorTree &DT,\n-                          const SmallPtrSetImpl<const Value *> *EphValues,\n-                          unsigned MaxUsesToExplore) {\n+Instruction *llvm::FindEarliestCapture(const Value *V, Function &F,\n+                                       bool ReturnCaptures, bool StoreCaptures,\n+                                       const DominatorTree &DT,\n+                                       unsigned MaxUsesToExplore) {\n   assert(!isa<GlobalValue>(V) &&\n          \"It doesn't make sense to ask whether a global is captured.\");\n \n-  EarliestCaptures CB(ReturnCaptures, F, DT, EphValues);\n+  EarliestCaptures CB(ReturnCaptures, F, DT);\n   PointerMayBeCaptured(V, &CB, MaxUsesToExplore);\n   if (CB.Captured)\n     ++NumCapturedBefore;\ndiff --git a/llvm/lib/Transforms/Scalar/DeadStoreElimination.cpp b/llvm/lib/Transforms/Scalar/DeadStoreElimination.cpp\nindex cacefc9718f1..a7b2c95e5b2c 100644\n--- a/llvm/lib/Transforms/Scalar/DeadStoreElimination.cpp\n+++ b/llvm/lib/Transforms/Scalar/DeadStoreElimination.cpp\n@@ -38,9 +38,7 @@\n #include \"llvm/ADT/Statistic.h\"\n #include \"llvm/ADT/StringRef.h\"\n #include \"llvm/Analysis/AliasAnalysis.h\"\n-#include \"llvm/Analysis/AssumptionCache.h\"\n #include \"llvm/Analysis/CaptureTracking.h\"\n-#include \"llvm/Analysis/CodeMetrics.h\"\n #include \"llvm/Analysis/GlobalsModRef.h\"\n #include \"llvm/Analysis/LoopInfo.h\"\n #include \"llvm/Analysis/MemoryBuiltins.h\"\n@@ -842,9 +840,6 @@ struct DSEState {\n   // Post-order numbers for each basic block. Used to figure out if memory\n   // accesses are executed before another access.\n   DenseMap<BasicBlock *, unsigned> PostOrderNumbers;\n-  // Values that are only used with assumes. Used to refine pointer escape\n-  // analysis.\n-  SmallPtrSet<const Value *, 32> EphValues;\n \n   /// Keep track of instructions (partly) overlapping with killing MemoryDefs per\n   /// basic block.\n@@ -864,10 +859,10 @@ struct DSEState {\n   DSEState &operator=(const DSEState &) = delete;\n \n   DSEState(Function &F, AliasAnalysis &AA, MemorySSA &MSSA, DominatorTree &DT,\n-           PostDominatorTree &PDT, AssumptionCache &AC,\n-           const TargetLibraryInfo &TLI, const LoopInfo &LI)\n-      : F(F), AA(AA), EI(DT, &LI, &EphValues), BatchAA(AA, &EI), MSSA(MSSA),\n-        DT(DT), PDT(PDT), TLI(TLI), DL(F.getParent()->getDataLayout()), LI(LI) {\n+           PostDominatorTree &PDT, const TargetLibraryInfo &TLI,\n+           const LoopInfo &LI)\n+      : F(F), AA(AA), EI(DT, &LI), BatchAA(AA, &EI), MSSA(MSSA), DT(DT),\n+        PDT(PDT), TLI(TLI), DL(F.getParent()->getDataLayout()), LI(LI) {\n     // Collect blocks with throwing instructions not modeled in MemorySSA and\n     // alloc-like objects.\n     unsigned PO = 0;\n@@ -897,8 +892,6 @@ struct DSEState {\n     AnyUnreachableExit = any_of(PDT.roots(), [](const BasicBlock *E) {\n       return isa<UnreachableInst>(E->getTerminator());\n     });\n-\n-    CodeMetrics::collectEphemeralValues(&F, &AC, EphValues);\n   }\n \n   LocationSize strengthenLocationSize(const Instruction *I,\n@@ -1075,7 +1068,7 @@ struct DSEState {\n       if (!isInvisibleToCallerOnUnwind(V)) {\n         I.first->second = false;\n       } else if (isNoAliasCall(V)) {\n-        I.first->second = !PointerMayBeCaptured(V, true, false, EphValues);\n+        I.first->second = !PointerMayBeCaptured(V, true, false);\n       }\n     }\n     return I.first->second;\n@@ -1094,7 +1087,7 @@ struct DSEState {\n       // with the killing MemoryDef. But we refrain from doing so for now to\n       // limit compile-time and this does not cause any changes to the number\n       // of stores removed on a large test set in practice.\n-      I.first->second = PointerMayBeCaptured(V, false, true, EphValues);\n+      I.first->second = PointerMayBeCaptured(V, false, true);\n     return !I.first->second;\n   }\n \n@@ -2065,12 +2058,11 @@ struct DSEState {\n \n static bool eliminateDeadStores(Function &F, AliasAnalysis &AA, MemorySSA &MSSA,\n                                 DominatorTree &DT, PostDominatorTree &PDT,\n-                                AssumptionCache &AC,\n                                 const TargetLibraryInfo &TLI,\n                                 const LoopInfo &LI) {\n   bool MadeChange = false;\n \n-  DSEState State(F, AA, MSSA, DT, PDT, AC, TLI, LI);\n+  DSEState State(F, AA, MSSA, DT, PDT, TLI, LI);\n   // For each store:\n   for (unsigned I = 0; I < State.MemDefs.size(); I++) {\n     MemoryDef *KillingDef = State.MemDefs[I];\n@@ -2251,10 +2243,9 @@ PreservedAnalyses DSEPass::run(Function &F, FunctionAnalysisManager &AM) {\n   DominatorTree &DT = AM.getResult<DominatorTreeAnalysis>(F);\n   MemorySSA &MSSA = AM.getResult<MemorySSAAnalysis>(F).getMSSA();\n   PostDominatorTree &PDT = AM.getResult<PostDominatorTreeAnalysis>(F);\n-  AssumptionCache &AC = AM.getResult<AssumptionAnalysis>(F);\n   LoopInfo &LI = AM.getResult<LoopAnalysis>(F);\n \n-  bool Changed = eliminateDeadStores(F, AA, MSSA, DT, PDT, AC, TLI, LI);\n+  bool Changed = eliminateDeadStores(F, AA, MSSA, DT, PDT, TLI, LI);\n \n #ifdef LLVM_ENABLE_STATS\n   if (AreStatisticsEnabled())\n",
  "tests": [
    {
      "file": "llvm/test/Transforms/DeadStoreElimination/assume.ll",
      "commands": [
        [
          "opt -passes=dse -S < %s",
          "FileCheck %s"
        ]
      ],
      "tests": [
        {
          "test_name": "f",
          "test_body": "@global = external constant i8\n\ndefine void @f() {\n; CHECK-LABEL: @f(\n; CHECK-NEXT:    [[TMP1:%.*]] = call noalias ptr @_Znwm(i64 32)\n; CHECK-NEXT:    [[TMP2:%.*]] = icmp ugt ptr [[TMP1]], @global\n; CHECK-NEXT:    call void @llvm.assume(i1 [[TMP2]])\n; CHECK-NEXT:    store i8 0, ptr [[TMP1]], align 1\n; CHECK-NEXT:    ret void\n  %tmp1 = call noalias ptr @_Znwm(i64 32)\n  %tmp2 = icmp ugt ptr %tmp1, @global\n  call void @llvm.assume(i1 %tmp2)\n  store i8 0, ptr %tmp1, align 1\n  ret void\n}\n\ndeclare ptr @_Znwm(i64)\n\n; Function Attrs: nocallback nofree nosync nounwind willreturn memory(inaccessiblemem: write)\ndeclare void @llvm.assume(i1 noundef) #0\n\nattributes #0 = { nocallback nofree nosync nounwind willreturn memory(inaccessiblemem: write) }",
          "source_program": "@global = external constant i8\n\ndefine void @f() {\n  %tmp1 = call noalias ptr @_Znwm(i64 32)\n  %tmp2 = icmp ugt ptr %tmp1, @global\n  call void @llvm.assume(i1 %tmp2)\n  store i8 0, ptr %tmp1, align 1\n  ret void\n}\n\ndeclare ptr @_Znwm(i64)\n\n; Function Attrs: nocallback nofree nosync nounwind willreturn memory(inaccessiblemem: write)\ndeclare void @llvm.assume(i1 noundef) #0\n\nattributes #0 = { nocallback nofree nosync nounwind willreturn memory(inaccessiblemem: write) }\n"
        },
        {
          "test_name": "pr70547",
          "test_body": "define void @pr70547() {\n; CHECK-LABEL: @pr70547(\n; CHECK-NEXT:    [[A:%.*]] = alloca i8, align 1\n; CHECK-NEXT:    store i8 0, ptr [[A]], align 1\n; CHECK-NEXT:    [[CALL:%.*]] = call ptr @quux(ptr [[A]]) #[[ATTR1:[0-9]+]]\n; CHECK-NEXT:    [[V:%.*]] = load i8, ptr [[CALL]], align 1\n; CHECK-NEXT:    [[CMP:%.*]] = icmp ne i8 [[V]], 1\n; CHECK-NEXT:    call void @llvm.assume(i1 [[CMP]])\n; CHECK-NEXT:    ret void\n  %a = alloca i8, align 1\n  store i8 0, ptr %a, align 1\n  %call = call ptr @quux(ptr %a) #1\n  %v = load i8, ptr %call, align 1\n  %cmp = icmp ne i8 %v, 1\n  call void @llvm.assume(i1 %cmp)\n  ret void\n}\n\n; Function Attrs: nocallback nofree nosync nounwind willreturn memory(inaccessiblemem: write)\ndeclare void @llvm.assume(i1 noundef) #0\n\ndeclare void @quux(ptr)\n\nattributes #0 = { nocallback nofree nosync nounwind willreturn memory(inaccessiblemem: write) }\nattributes #1 = { nounwind willreturn memory(none) }",
          "source_program": "define void @pr70547() {\n  %a = alloca i8, align 1\n  store i8 0, ptr %a, align 1\n  %call = call ptr @quux(ptr %a) #1\n  %v = load i8, ptr %call, align 1\n  %cmp = icmp ne i8 %v, 1\n  call void @llvm.assume(i1 %cmp)\n  ret void\n}\n\n; Function Attrs: nocallback nofree nosync nounwind willreturn memory(inaccessiblemem: write)\ndeclare void @llvm.assume(i1 noundef) #0\n\ndeclare void @quux(ptr)\n\nattributes #0 = { nocallback nofree nosync nounwind willreturn memory(inaccessiblemem: write) }\nattributes #1 = { nounwind willreturn memory(none) }\n"
        },
        {
          "test_name": "f2",
          "test_body": "@global = external constant i8\n\ndefine void @f2() {\n; CHECK-LABEL: @f2(\n; CHECK-NEXT:    [[TMP1:%.*]] = call noalias ptr @_Znwm(i64 32)\n; CHECK-NEXT:    [[TMP2:%.*]] = icmp ugt ptr [[TMP1]], @global\n; CHECK-NEXT:    call void @llvm.assume(i1 [[TMP2]])\n; CHECK-NEXT:    store i8 0, ptr [[TMP1]], align 1\n; CHECK-NEXT:    call void @quux(ptr @global)\n; CHECK-NEXT:    ret void\n  %tmp1 = call noalias ptr @_Znwm(i64 32)\n  %tmp2 = icmp ugt ptr %tmp1, @global\n  call void @llvm.assume(i1 %tmp2)\n  store i8 0, ptr %tmp1, align 1\n  call void @quux(ptr @global)\n  ret void\n}\n\ndeclare ptr @_Znwm(i64)\n\n; Function Attrs: nocallback nofree nosync nounwind willreturn memory(inaccessiblemem: write)\ndeclare void @llvm.assume(i1 noundef) #0\n\ndeclare void @quux(ptr)\n\nattributes #0 = { nocallback nofree nosync nounwind willreturn memory(inaccessiblemem: write) }",
          "source_program": "@global = external constant i8\n\ndefine void @f2() {\n  %tmp1 = call noalias ptr @_Znwm(i64 32)\n  %tmp2 = icmp ugt ptr %tmp1, @global\n  call void @llvm.assume(i1 %tmp2)\n  store i8 0, ptr %tmp1, align 1\n  call void @quux(ptr @global)\n  ret void\n}\n\ndeclare ptr @_Znwm(i64)\n\n; Function Attrs: nocallback nofree nosync nounwind willreturn memory(inaccessiblemem: write)\ndeclare void @llvm.assume(i1 noundef) #0\n\ndeclare void @quux(ptr)\n\nattributes #0 = { nocallback nofree nosync nounwind willreturn memory(inaccessiblemem: write) }\n"
        }
      ]
    }
  ],
  "issue": {
    "title": "Wrong code at -O2 on x86_64-linux_gnu since Clang-15",
    "body": "clang at -O2 produced the wrong code.\r\n\r\nBisected to b22ffc7b98f8700d7d480127ff1c3683a6dac6e5, which was committed by @aeubanks \r\n\r\nCompiler explorer: https://godbolt.org/z/MxrnaqTqc\r\n\r\n\r\n```console\r\n% cat a.c\r\nint printf(const char *, ...);\r\nint a;\r\nstatic int b;\r\nshort(c)(short d, int e) { return d >> e; }\r\nchar *f(int d, char *e) {\r\n  if ((d & 1) == 0)\r\n    return e;\r\n  switch (d) {\r\n  case 7:\r\n  case 49:\r\n  case 1:\r\n    return \"\";\r\n  case 11:\r\n    return \"0\";\r\n  case 3:\r\n    return \"0\";\r\n  }\r\n  return \"1\";\r\n}\r\nchar g(int d) {\r\n  char h = 0, i = *f(d, &h);\r\n  return i;\r\n}\r\nchar j(int d) {\r\n  for (;;) {\r\n    if (g(d + 7) + d)\r\n      return 0;\r\n    for (; b - 30; b+=0)\r\n      ;\r\n  }\r\n}\r\nvoid k() {\r\n  int l = -8, m = c(l, 8);\r\n  j(m);\r\n}\r\nint main() {\r\n  k();\r\n  printf(\"%X\\n\", a);\r\n}\r\n% \r\n% clang -O0 a.c && ./a.out\r\n0\r\n% clang -O2 a.c && ./a.out\r\n%\r\n```",
    "author": "shao-hua-li",
    "labels": [
      "miscompilation",
      "llvm:analysis",
      "llvm:transforms"
    ],
    "comments": [
      {
        "author": "nikic",
        "body": "Reduced test case:\r\n```llvm\r\n; RUN: opt -S -passes=dse < %s\r\ndefine void @test() {\r\nentry:\r\n  %a = alloca i8\r\n  store i8 0, ptr %a\r\n  %call = call ptr @f(ptr %a) memory(none) nounwind willreturn\r\n  %v = load i8, ptr %call\r\n  %cmp = icmp ne i8 %v, 1\r\n  call void @llvm.assume(i1 %cmp)\r\n  ret void\r\n}\r\n\r\ndeclare ptr @f(ptr)\r\ndeclare void @llvm.assume(i1)\r\n```\r\nThis ends up dropping the store."
      },
      {
        "author": "nikic",
        "body": "Similar case as https://reviews.llvm.org/D153464."
      }
    ]
  },
  "properties": {
    "is_single_file_fix": false,
    "is_single_func_fix": false
  }
}