{
  "pr_id": 198194,
  "pr_url": "https://github.com/llvm/llvm-project/pull/198194",
  "state": "open",
  "title": "[SLP] Prefer outer binary op when opcode groups tie in buildInstructionsState",
  "author": "alexey-bataev",
  "base_commit": "195c622972390b7894bb3aaa15ceee3cfb648db5",
  "fix_commit": "5d516981d19f819b12c314547d5c74928fe54c39",
  "patch": "diff --git a/llvm/lib/Transforms/Vectorize/SLPVectorizer.cpp b/llvm/lib/Transforms/Vectorize/SLPVectorizer.cpp\nindex 898115005a7dd..a6f4f7f5526ca 100644\n--- a/llvm/lib/Transforms/Vectorize/SLPVectorizer.cpp\n+++ b/llvm/lib/Transforms/Vectorize/SLPVectorizer.cpp\n@@ -11739,6 +11739,23 @@ class InstructionsCompatibilityAnalysis {\n             return Operands.contains(I);\n           }))\n         continue;\n+      // On a tie, keep the outer binary op as MainOp rather than replacing it\n+      // with an inner op that appears as its direct operand. For example, in\n+      // (2.0f * A) + B the fadd and fmul each appear once in VL; without this\n+      // check the fmul could win and prevent vectorization of the fadd pair.\n+      if (P.second.size() == BestOpcodeNum) {\n+        auto *I = P.second.front();\n+        if (auto *MainBO = dyn_cast<BinaryOperator>(MainOp)) {\n+          auto *MainBOOp0 = dyn_cast<Instruction>(MainBO->getOperand(0));\n+          auto *MainBOOp1 = dyn_cast<Instruction>(MainBO->getOperand(1));\n+          if (MainBOOp0 && MainBOOp0->getOpcode() == I->getOpcode() &&\n+              MainBOOp0->getParent() == I->getParent())\n+            continue;\n+          if (MainBOOp1 && MainBOOp1->getOpcode() == I->getOpcode() &&\n+              MainBOOp1->getParent() == I->getParent())\n+            continue;\n+        }\n+      }\n       UsedOutside = PUsedOutside;\n       for (Instruction *I : P.second) {\n         if (IsSupportedInstruction(I, AnyUndef)) {\n",
  "components": [
    "SLPVectorizer"
  ],
  "description": "When VL contains instructions of different opcodes with equal counts,\nthe tie-breaking in buildInstructionsState could replace an outer\noperation (e.g., fadd) with an inner one (e.g., fmul) that appears as\nits direct operand, depending on SmallMapVector iteration order. Add a\ncheck: if the current MainOp is a BinaryOperator with a direct operand\nmatching the challenger partition's opcode in the same block, keep\nMainOp instead of switching to the inner operation.\n\nPartially fixes #43353\n",
  "tests": [
    {
      "file": "llvm/test/Transforms/PhaseOrdering/X86/avg.ll",
      "commands": [
        "opt < %s -O3 -S -mtriple=x86_64-- -mcpu=x86-64",
        "opt < %s -O3 -S -mtriple=x86_64-- -mcpu=x86-64-v2",
        "opt < %s -O3 -S -mtriple=x86_64-- -mcpu=x86-64-v3",
        "opt < %s -O3 -S -mtriple=x86_64-- -mcpu=x86-64-v4",
        "opt < %s -passes=\"default<O3>\" -S -mtriple=x86_64-- -mcpu=x86-64",
        "opt < %s -passes=\"default<O3>\" -S -mtriple=x86_64-- -mcpu=x86-64-v2",
        "opt < %s -passes=\"default<O3>\" -S -mtriple=x86_64-- -mcpu=x86-64-v3",
        "opt < %s -passes=\"default<O3>\" -S -mtriple=x86_64-- -mcpu=x86-64-v4"
      ],
      "tests": [
        {
          "test_name": "avgr_16_u8",
          "test_body": "%\"struct.std::array16\" = type { [16 x i8] }\n\ndefine { i64, i64 } @avgr_16_u8(i64 %a.coerce0, i64 %a.coerce1, i64 %b.coerce0, i64 %b.coerce1) {\nentry:\n  %retval = alloca %\"struct.std::array16\", align 1\n  %a = alloca %\"struct.std::array16\", align 1\n  %b = alloca %\"struct.std::array16\", align 1\n  store i64 %a.coerce0, ptr %a, align 1\n  %0 = getelementptr inbounds nuw i8, ptr %a, i64 8\n  store i64 %a.coerce1, ptr %0, align 1\n  store i64 %b.coerce0, ptr %b, align 1\n  %1 = getelementptr inbounds nuw i8, ptr %b, i64 8\n  store i64 %b.coerce1, ptr %1, align 1\n  br label %for.cond\n\nfor.cond:                                         ; preds = %for.body, %entry\n  %i.0 = phi i64 [ 0, %entry ], [ %inc, %for.body ]\n  %cmp = icmp samesign ult i64 %i.0, 16\n  br i1 %cmp, label %for.body, label %for.cond.cleanup\n\nfor.cond.cleanup:                                 ; preds = %for.cond\n  %.fca.0.load = load i64, ptr %retval, align 1\n  %.fca.0.insert = insertvalue { i64, i64 } poison, i64 %.fca.0.load, 0\n  %.fca.1.gep = getelementptr inbounds nuw i8, ptr %retval, i64 8\n  %.fca.1.load = load i64, ptr %.fca.1.gep, align 1\n  %.fca.1.insert = insertvalue { i64, i64 } %.fca.0.insert, i64 %.fca.1.load, 1\n  ret { i64, i64 } %.fca.1.insert\n\nfor.body:                                         ; preds = %for.cond\n  %arrayidx.i = getelementptr inbounds nuw i8, ptr %a, i64 %i.0\n  %2 = load i8, ptr %arrayidx.i, align 1\n  %conv1 = zext i8 %2 to i16\n  %arrayidx.i12 = getelementptr inbounds nuw i8, ptr %b, i64 %i.0\n  %3 = load i8, ptr %arrayidx.i12, align 1\n  %conv4 = zext i8 %3 to i16\n  %add = add nuw nsw i16 %conv1, %conv4\n  %add5 = add nuw nsw i16 %add, 1\n  %shr = lshr i16 %add5, 1\n  %conv6 = trunc i16 %shr to i8\n  %arrayidx.i13 = getelementptr inbounds nuw i8, ptr %retval, i64 %i.0\n  store i8 %conv6, ptr %arrayidx.i13, align 1\n  %inc = add nuw nsw i64 %i.0, 1\n  br label %for.cond\n}\n"
        },
        {
          "test_name": "avgr_8_u16",
          "test_body": "%\"struct.std::array8\" = type { [8 x i16] }\n\ndefine { i64, i64 } @avgr_8_u16(i64 %a.coerce0, i64 %a.coerce1, i64 %b.coerce0, i64 %b.coerce1) {\nentry:\n  %retval = alloca %\"struct.std::array8\", align 2\n  %a = alloca %\"struct.std::array8\", align 2\n  %b = alloca %\"struct.std::array8\", align 2\n  store i64 %a.coerce0, ptr %a, align 2\n  %0 = getelementptr inbounds nuw i8, ptr %a, i64 8\n  store i64 %a.coerce1, ptr %0, align 2\n  store i64 %b.coerce0, ptr %b, align 2\n  %1 = getelementptr inbounds nuw i8, ptr %b, i64 8\n  store i64 %b.coerce1, ptr %1, align 2\n  br label %for.cond\n\nfor.cond:                                         ; preds = %for.body, %entry\n  %i.0 = phi i64 [ 0, %entry ], [ %inc, %for.body ]\n  %cmp = icmp samesign ult i64 %i.0, 8\n  br i1 %cmp, label %for.body, label %for.cond.cleanup\n\nfor.cond.cleanup:                                 ; preds = %for.cond\n  %.fca.0.load = load i64, ptr %retval, align 2\n  %.fca.0.insert = insertvalue { i64, i64 } poison, i64 %.fca.0.load, 0\n  %.fca.1.gep = getelementptr inbounds nuw i8, ptr %retval, i64 8\n  %.fca.1.load = load i64, ptr %.fca.1.gep, align 2\n  %.fca.1.insert = insertvalue { i64, i64 } %.fca.0.insert, i64 %.fca.1.load, 1\n  ret { i64, i64 } %.fca.1.insert\n\nfor.body:                                         ; preds = %for.cond\n  %arrayidx.i = getelementptr inbounds nuw [2 x i8], ptr %a, i64 %i.0\n  %2 = load i16, ptr %arrayidx.i, align 2\n  %conv = zext i16 %2 to i32\n  %arrayidx.i10 = getelementptr inbounds nuw [2 x i8], ptr %b, i64 %i.0\n  %3 = load i16, ptr %arrayidx.i10, align 2\n  %conv2 = zext i16 %3 to i32\n  %add = add nuw nsw i32 %conv, %conv2\n  %add3 = add nuw nsw i32 %add, 1\n  %shr = lshr i32 %add3, 1\n  %conv4 = trunc nuw i32 %shr to i16\n  %arrayidx.i11 = getelementptr inbounds nuw [2 x i8], ptr %retval, i64 %i.0\n  store i16 %conv4, ptr %arrayidx.i11, align 2\n  %inc = add nuw nsw i64 %i.0, 1\n  br label %for.cond\n}\n"
        }
      ]
    },
    {
      "file": "llvm/test/Transforms/SLPVectorizer/X86/complex-fma-combine.ll",
      "commands": [
        "opt -S --passes=slp-vectorizer -mtriple=x86_64-unknown-linux -mcpu=skylake < %s"
      ],
      "tests": [
        {
          "test_name": "fma_f32",
          "test_body": "define <2 x float> @fma_f32(ptr %A, float %B) {\nentry:\n  %0 = load <2 x float>, ptr %A, align 4\n  %retval.sroa.0.0.vec.extract.i = extractelement <2 x float> %0, i64 0\n  %retval.sroa.0.4.vec.extract.i = extractelement <2 x float> %0, i64 1\n  %mul.rl.i.i = fmul float %retval.sroa.0.0.vec.extract.i, 2.000000e+00\n  %mul.il.i.i = fmul float %retval.sroa.0.4.vec.extract.i, 2.000000e+00\n  %add.r.i.i = fadd float %B, %mul.rl.i.i\n  %1 = insertelement <2 x float> poison, float %add.r.i.i, i64 0\n  %retval.sroa.0.0.vec.insert.i6 = insertelement <2 x float> %1, float %mul.il.i.i, i64 1\n  ret <2 x float> %retval.sroa.0.0.vec.insert.i6\n}\n"
        }
      ]
    },
    {
      "file": "llvm/test/Transforms/SLPVectorizer/X86/gathered-loads-non-full-reg.ll",
      "commands": [
        "opt -S --passes=slp-vectorizer -mtriple=x86_64-unknown-linux -mcpu=cascadelake < %s"
      ],
      "tests": [
        {
          "test_name": "test",
          "test_body": "@solid_ = external global [608 x i8]\n\ndefine void @test(ptr noalias %0) {\n.lr.ph1019:\n  %1 = getelementptr i8, ptr %0, i64 8\n  %2 = getelementptr i8, ptr %0, i64 32\n  %3 = getelementptr i8, ptr %0, i64 128\n  %4 = getelementptr i8, ptr %0, i64 200\n  %5 = getelementptr i8, ptr %0, i64 208\n  %6 = getelementptr i8, ptr %0, i64 232\n  %7 = getelementptr i8, ptr %0, i64 288\n  %8 = getelementptr i8, ptr %0, i64 320\n  %9 = getelementptr i8, ptr %0, i64 304\n  %10 = getelementptr i8, ptr %0, i64 424\n  %11 = getelementptr i8, ptr %0, i64 480\n  %12 = getelementptr i8, ptr %0, i64 504\n  %13 = getelementptr i8, ptr %0, i64 632\n  %14 = getelementptr i8, ptr %0, i64 720\n  %15 = load double, ptr %1, align 8\n  %16 = load double, ptr %2, align 8\n  %17 = fadd double %16, %15\n  %18 = load double, ptr %3, align 8\n  %19 = load double, ptr %4, align 8\n  %20 = load double, ptr %5, align 8\n  %21 = load double, ptr %6, align 8\n  %22 = fadd double %21, %20\n  %23 = load double, ptr %7, align 8\n  %24 = load double, ptr %8, align 8\n  %25 = load double, ptr %9, align 8\n  %26 = load double, ptr %10, align 8\n  %27 = load double, ptr %11, align 8\n  %28 = load double, ptr %12, align 8\n  %29 = fadd double %28, %27\n  %30 = fmul double %22, %18\n  %31 = fmul double %30, 0.000000e+00\n  %32 = fsub double 0.000000e+00, %25\n  %33 = fmul double %32, 0.000000e+00\n  %34 = fadd double %33, 0.000000e+00\n  %35 = fmul double %34, 0.000000e+00\n  %36 = fmul double %29, %26\n  %37 = fmul double %36, 0.000000e+00\n  %38 = fadd double %37, 0.000000e+00\n  %39 = fsub double %17, %19\n  %40 = fmul double %39, %23\n  %41 = fmul double %40, 0.000000e+00\n  %42 = load double, ptr %0, align 8\n  %43 = load double, ptr %13, align 8\n  %44 = fmul double %43, %31\n  %45 = load double, ptr %14, align 8\n  %46 = fmul double %35, 0.000000e+00\n  %47 = fadd double %44, 0.000000e+00\n  %48 = fmul double %45, %38\n  %49 = fmul double %45, %41\n  store double %46, ptr getelementptr inbounds (i8, ptr @solid_, i64 384), align 8\n  store double %47, ptr getelementptr inbounds (i8, ptr @solid_, i64 408), align 8\n  store double %48, ptr getelementptr inbounds (i8, ptr @solid_, i64 392), align 8\n  store double %49, ptr getelementptr inbounds (i8, ptr @solid_, i64 400), align 8\n  %.neg965 = fmul double %48, %24\n  %reass.add993 = fadd double %.neg965, 0.000000e+00\n  %50 = fadd double %42, %reass.add993\n  %51 = fsub double 0.000000e+00, %50\n  store double %51, ptr getelementptr inbounds (i8, ptr @solid_, i64 296), align 8\n  %.neg969 = fmul double %49, 0.000000e+00\n  %reass.add996 = fadd double %.neg969, 0.000000e+00\n  %52 = fadd double %45, %reass.add996\n  %53 = fsub double 0.000000e+00, %52\n  store double %53, ptr getelementptr inbounds (i8, ptr @solid_, i64 304), align 8\n  ret void\n}\n"
        }
      ]
    },
    {
      "file": "llvm/test/Transforms/SLPVectorizer/buildvector-nodes-dependency.ll",
      "commands": [
        "%if x86-registered-target %{ opt -passes=slp-vectorizer -S -mtriple=x86_64 < %s",
        "%if aarch64-registered-target %{ opt -passes=slp-vectorizer -S -mtriple=aarch64-unknown-linux-gnu < %s"
      ],
      "tests": [
        {
          "test_name": "test",
          "test_body": "define double @test() {\nentry:\n  %0 = load double, ptr null, align 8\n  br label %cond.true\n\ncond.true:                                        ; preds = %entry\n  %mul13 = fmul double %0, 0.000000e+00\n  %mul14 = fmul double %0, 0.000000e+00\n  %mul15 = fmul double %mul14, 0.000000e+00\n  %mul16 = fmul double 0.000000e+00, %mul15\n  %add17 = fadd double %mul13, %mul16\n  %sub18 = fsub double %add17, 0.000000e+00\n  %mul19 = fmul double %0, 0.000000e+00\n  %mul20 = fmul double %mul19, 0.000000e+00\n  %mul21 = fmul double %mul20, 0.000000e+00\n  %add22 = fadd double %sub18, %mul21\n  %sub23 = fsub double %add22, 0.000000e+00\n  %mul24 = fmul double %0, 0.000000e+00\n  %mul25 = fmul double %mul24, 0.000000e+00\n  %mul26 = fmul double 0.000000e+00, %mul25\n  %add27 = fadd double %mul26, %sub23\n  %mul = fmul double 0.000000e+00, 0.000000e+00\n  %mul1 = fmul double %mul, 0.000000e+00\n  %sub = fsub double %mul1, 0.000000e+00\n  %add = fadd double 0.000000e+00, %sub\n  %sub2 = fsub double %add, %mul\n  %sub3 = fsub double %sub2, 0.000000e+00\n  %mul4 = fmul double %0, 0.000000e+00\n  %mul5 = fmul double %mul4, 0.000000e+00\n  %mul6 = fmul double 0.000000e+00, %mul5\n  %add7 = fadd double %mul6, %sub3\n  %sub8 = fsub double %add7, 0.000000e+00\n  %mul9 = fmul double %0, 0.000000e+00\n  %mul10 = fmul double %mul9, 0.000000e+00\n  %mul11 = fmul double 0.000000e+00, %mul10\n  %add12 = fadd double %mul11, %sub8\n  %add29 = fadd double %add12, %add27\n  ret double %add29\n}\n"
        }
      ]
    }
  ],
  "labels": [
    "vectorizers",
    "llvm:transforms"
  ],
  "comments": [
    {
      "author": "llvmorg-github-actions[bot]",
      "body": "\n<!--LLVM PR SUMMARY COMMENT-->\n@llvm/pr-subscribers-vectorizers\n\n@llvm/pr-subscribers-llvm-transforms\n\nAuthor: Alexey Bataev (alexey-bataev)\n\n<details>\n<summary>Changes</summary>\n\nWhen VL contains instructions of different opcodes with equal counts,\nthe tie-breaking in buildInstructionsState could replace an outer\noperation (e.g., fadd) with an inner one (e.g., fmul) that appears as\nits direct operand, depending on SmallMapVector iteration order. Add a\ncheck: if the current MainOp is a BinaryOperator with a direct operand\nmatching the challenger partition's opcode in the same block, keep\nMainOp instead of switching to the inner operation.\n\nPartially fixes #<!-- -->43353\n\n\n---\n\nPatch is 25.63 KiB, truncated to 20.00 KiB below, full version: https://github.com/llvm/llvm-project/pull/198194.diff\n\n\n5 Files Affected:\n\n- (modified) llvm/lib/Transforms/Vectorize/SLPVectorizer.cpp (+17) \n- (modified) llvm/test/Transforms/PhaseOrdering/X86/avg.ll (+31-42) \n- (modified) llvm/test/Transforms/SLPVectorizer/X86/complex-fma-combine.ll (+3-7) \n- (modified) llvm/test/Transforms/SLPVectorizer/X86/gathered-loads-non-full-reg.ll (+25-24) \n- (modified) llvm/test/Transforms/SLPVectorizer/buildvector-nodes-dependency.ll (+6-10) \n\n\n``````````diff\ndiff --git a/llvm/lib/Transforms/Vectorize/SLPVectorizer.cpp b/llvm/lib/Transforms/Vectorize/SLPVectorizer.cpp\nindex 898115005a7dd..a6f4f7f5526ca 100644\n--- a/llvm/lib/Transforms/Vectorize/SLPVectorizer.cpp\n+++ b/llvm/lib/Transforms/Vectorize/SLPVectorizer.cpp\n@@ -11739,6 +11739,23 @@ class InstructionsCompatibilityAnalysis {\n             return Operands.contains(I);\n           }))\n         continue;\n+      // On a tie, keep the outer binary op as MainOp rather than replacing it\n+      // with an inner op that appears as its direct operand. For example, in\n+      // (2.0f * A) + B the fadd and fmul each appear once in VL; without this\n+      // check the fmul could win and prevent vectorization of the fadd pair.\n+      if (P.second.size() == BestOpcodeNum) {\n+        auto *I = P.second.front();\n+        if (auto *MainBO = dyn_cast<BinaryOperator>(MainOp)) {\n+          auto *MainBOOp0 = dyn_cast<Instruction>(MainBO->getOperand(0));\n+          auto *MainBOOp1 = dyn_cast<Instruction>(MainBO->getOperand(1));\n+          if (MainBOOp0 && MainBOOp0->getOpcode() == I->getOpcode() &&\n+              MainBOOp0->getParent() == I->getParent())\n+            continue;\n+          if (MainBOOp1 && MainBOOp1->getOpcode() == I->getOpcode() &&\n+              MainBOOp1->getParent() == I->getParent())\n+            continue;\n+        }\n+      }\n       UsedOutside = PUsedOutside;\n       for (Instruction *I : P.second) {\n         if (IsSupportedInstruction(I, AnyUndef)) {\ndiff --git a/llvm/test/Transforms/PhaseOrdering/X86/avg.ll b/llvm/test/Transforms/PhaseOrdering/X86/avg.ll\nindex e28e294164ac5..0b0ade31da145 100644\n--- a/llvm/test/Transforms/PhaseOrdering/X86/avg.ll\n+++ b/llvm/test/Transforms/PhaseOrdering/X86/avg.ll\n@@ -42,13 +42,13 @@ define { i64, i64 } @avgr_16_u8(i64 %a.coerce0, i64 %a.coerce1, i64 %b.coerce0,\n ; SSE2-NEXT:    [[TMP18:%.*]] = insertelement <2 x i16> poison, i16 [[TMP0]], i64 0\n ; SSE2-NEXT:    [[TMP19:%.*]] = insertelement <2 x i16> [[TMP18]], i16 [[TMP7]], i64 1\n ; SSE2-NEXT:    [[TMP20:%.*]] = lshr <2 x i16> [[TMP19]], splat (i16 8)\n+; SSE2-NEXT:    [[A_SROA_17_8_EXTRACT_SHIFT:%.*]] = lshr i64 [[A_COERCE1]], 56\n ; SSE2-NEXT:    [[B_SROA_8_0_EXTRACT_SHIFT:%.*]] = lshr i64 [[B_COERCE0]], 56\n ; SSE2-NEXT:    [[TMP21:%.*]] = insertelement <2 x i16> poison, i16 [[TMP8]], i64 0\n ; SSE2-NEXT:    [[TMP22:%.*]] = insertelement <2 x i16> [[TMP21]], i16 [[TMP15]], i64 1\n ; SSE2-NEXT:    [[TMP23:%.*]] = lshr <2 x i16> [[TMP22]], splat (i16 8)\n-; SSE2-NEXT:    [[A_SROA_17_8_EXTRACT_SHIFT:%.*]] = lshr i64 [[A_COERCE1]], 56\n-; SSE2-NEXT:    [[CONV1_6:%.*]] = and i64 [[A_SROA_7_0_EXTRACT_SHIFT]], 255\n ; SSE2-NEXT:    [[B_SROA_17_8_EXTRACT_SHIFT:%.*]] = lshr i64 [[B_COERCE1]], 56\n+; SSE2-NEXT:    [[CONV1_6:%.*]] = and i64 [[A_SROA_7_0_EXTRACT_SHIFT]], 255\n ; SSE2-NEXT:    [[CONV4_6:%.*]] = and i64 [[B_SROA_7_0_EXTRACT_SHIFT]], 255\n ; SSE2-NEXT:    [[TMP24:%.*]] = add nuw nsw <2 x i64> [[TMP16]], splat (i64 1)\n ; SSE2-NEXT:    [[TMP25:%.*]] = add nuw nsw <2 x i64> [[TMP24]], [[TMP17]]\n@@ -144,13 +144,13 @@ define { i64, i64 } @avgr_16_u8(i64 %a.coerce0, i64 %a.coerce1, i64 %b.coerce0,\n ; SSE4-NEXT:    [[TMP18:%.*]] = insertelement <2 x i16> poison, i16 [[TMP0]], i64 0\n ; SSE4-NEXT:    [[TMP19:%.*]] = insertelement <2 x i16> [[TMP18]], i16 [[TMP7]], i64 1\n ; SSE4-NEXT:    [[TMP20:%.*]] = lshr <2 x i16> [[TMP19]], splat (i16 8)\n+; SSE4-NEXT:    [[A_SROA_17_8_EXTRACT_SHIFT:%.*]] = lshr i64 [[A_COERCE1]], 56\n ; SSE4-NEXT:    [[B_SROA_8_0_EXTRACT_SHIFT:%.*]] = lshr i64 [[B_COERCE0]], 56\n ; SSE4-NEXT:    [[TMP21:%.*]] = insertelement <2 x i16> poison, i16 [[TMP8]], i64 0\n ; SSE4-NEXT:    [[TMP22:%.*]] = insertelement <2 x i16> [[TMP21]], i16 [[TMP15]], i64 1\n ; SSE4-NEXT:    [[TMP23:%.*]] = lshr <2 x i16> [[TMP22]], splat (i16 8)\n-; SSE4-NEXT:    [[A_SROA_17_8_EXTRACT_SHIFT:%.*]] = lshr i64 [[A_COERCE1]], 56\n-; SSE4-NEXT:    [[CONV1_6:%.*]] = and i64 [[A_SROA_7_0_EXTRACT_SHIFT]], 255\n ; SSE4-NEXT:    [[B_SROA_17_8_EXTRACT_SHIFT:%.*]] = lshr i64 [[B_COERCE1]], 56\n+; SSE4-NEXT:    [[CONV1_6:%.*]] = and i64 [[A_SROA_7_0_EXTRACT_SHIFT]], 255\n ; SSE4-NEXT:    [[CONV4_6:%.*]] = and i64 [[B_SROA_7_0_EXTRACT_SHIFT]], 255\n ; SSE4-NEXT:    [[TMP24:%.*]] = add nuw nsw <2 x i64> [[TMP16]], splat (i64 1)\n ; SSE4-NEXT:    [[TMP25:%.*]] = add nuw nsw <2 x i64> [[TMP24]], [[TMP17]]\n@@ -747,11 +747,11 @@ define { i64, i64 } @avgr_8_u16(i64 %a.coerce0, i64 %a.coerce1, i64 %b.coerce0,\n ; SSE2-NEXT:    [[TMP19:%.*]] = insertelement <2 x i32> poison, i32 [[TMP0]], i64 0\n ; SSE2-NEXT:    [[TMP10:%.*]] = insertelement <2 x i32> [[TMP19]], i32 [[TMP2]], i64 1\n ; SSE2-NEXT:    [[TMP11:%.*]] = lshr <2 x i32> [[TMP10]], splat (i32 16)\n+; SSE2-NEXT:    [[CONV_6:%.*]] = lshr i64 [[A_COERCE1]], 48\n ; SSE2-NEXT:    [[CONV2_4:%.*]] = lshr i64 [[B_COERCE0]], 48\n ; SSE2-NEXT:    [[TMP20:%.*]] = lshr <2 x i32> [[TMP4]], splat (i32 16)\n-; SSE2-NEXT:    [[CONV_6:%.*]] = lshr i64 [[A_COERCE1]], 48\n-; SSE2-NEXT:    [[A_SROA_9_8_EXTRACT_SHIFT:%.*]] = and i64 [[A_SROA_3_0_EXTRACT_SHIFT]], 65535\n ; SSE2-NEXT:    [[B_SROA_9_8_EXTRACT_SHIFT:%.*]] = lshr i64 [[B_COERCE1]], 48\n+; SSE2-NEXT:    [[A_SROA_9_8_EXTRACT_SHIFT:%.*]] = and i64 [[A_SROA_3_0_EXTRACT_SHIFT]], 65535\n ; SSE2-NEXT:    [[CONV2_2:%.*]] = and i64 [[B_SROA_3_0_EXTRACT_SHIFT]], 65535\n ; SSE2-NEXT:    [[TMP31:%.*]] = add nuw nsw <2 x i64> [[TMP7]], splat (i64 1)\n ; SSE2-NEXT:    [[TMP14:%.*]] = add nuw nsw <2 x i64> [[TMP31]], [[TMP8]]\n@@ -810,11 +810,11 @@ define { i64, i64 } @avgr_8_u16(i64 %a.coerce0, i64 %a.coerce1, i64 %b.coerce0,\n ; SSE4-NEXT:    [[TMP9:%.*]] = insertelement <2 x i32> poison, i32 [[TMP0]], i64 0\n ; SSE4-NEXT:    [[TMP10:%.*]] = insertelement <2 x i32> [[TMP9]], i32 [[TMP1]], i64 1\n ; SSE4-NEXT:    [[TMP11:%.*]] = lshr <2 x i32> [[TMP10]], splat (i32 16)\n+; SSE4-NEXT:    [[A_SROA_9_8_EXTRACT_SHIFT:%.*]] = lshr i64 [[A_COERCE1]], 48\n ; SSE4-NEXT:    [[B_SROA_4_0_EXTRACT_SHIFT:%.*]] = lshr i64 [[B_COERCE0]], 48\n ; SSE4-NEXT:    [[TMP12:%.*]] = lshr <2 x i32> [[TMP4]], splat (i32 16)\n-; SSE4-NEXT:    [[A_SROA_9_8_EXTRACT_SHIFT:%.*]] = lshr i64 [[A_COERCE1]], 48\n-; SSE4-NEXT:    [[CONV_2:%.*]] = and i64 [[A_SROA_3_0_EXTRACT_SHIFT]], 65535\n ; SSE4-NEXT:    [[B_SROA_9_8_EXTRACT_SHIFT:%.*]] = lshr i64 [[B_COERCE1]], 48\n+; SSE4-NEXT:    [[CONV_2:%.*]] = and i64 [[A_SROA_3_0_EXTRACT_SHIFT]], 65535\n ; SSE4-NEXT:    [[CONV2_2:%.*]] = and i64 [[B_SROA_3_0_EXTRACT_SHIFT]], 65535\n ; SSE4-NEXT:    [[TMP13:%.*]] = add nuw nsw <2 x i64> [[TMP7]], splat (i64 1)\n ; SSE4-NEXT:    [[TMP14:%.*]] = add nuw nsw <2 x i64> [[TMP13]], [[TMP8]]\n@@ -856,28 +856,26 @@ define { i64, i64 } @avgr_8_u16(i64 %a.coerce0, i64 %a.coerce1, i64 %b.coerce0,\n ;\n ; AVX2-LABEL: @avgr_8_u16(\n ; AVX2-NEXT:  entry:\n-; AVX2-NEXT:    [[TMP0:%.*]] = trunc i64 [[A_COERCE0:%.*]] to i32\n-; AVX2-NEXT:    [[A_SROA_3_0_EXTRACT_SHIFT:%.*]] = lshr i64 [[A_COERCE0]], 32\n-; AVX2-NEXT:    [[A_SROA_4_0_EXTRACT_SHIFT:%.*]] = lshr i64 [[A_COERCE0]], 48\n ; AVX2-NEXT:    [[TMP1:%.*]] = trunc i64 [[A_COERCE1:%.*]] to i32\n-; AVX2-NEXT:    [[TMP2:%.*]] = insertelement <2 x i64> poison, i64 [[B_COERCE0:%.*]], i64 0\n-; AVX2-NEXT:    [[TMP20:%.*]] = insertelement <2 x i64> [[TMP2]], i64 [[A_COERCE1]], i64 1\n+; AVX2-NEXT:    [[TMP2:%.*]] = insertelement <2 x i64> poison, i64 [[A_COERCE1]], i64 0\n+; AVX2-NEXT:    [[TMP6:%.*]] = insertelement <2 x i64> [[TMP2]], i64 [[A_COERCE2:%.*]], i64 1\n+; AVX2-NEXT:    [[TMP5:%.*]] = lshr <2 x i64> [[TMP6]], <i64 32, i64 48>\n+; AVX2-NEXT:    [[A_SROA_4_0_EXTRACT_SHIFT:%.*]] = lshr i64 [[A_COERCE1]], 48\n+; AVX2-NEXT:    [[TMP18:%.*]] = trunc i64 [[A_COERCE2]] to i32\n+; AVX2-NEXT:    [[TMP20:%.*]] = insertelement <2 x i64> [[TMP6]], i64 [[B_COERCE0:%.*]], i64 0\n ; AVX2-NEXT:    [[TMP21:%.*]] = lshr <2 x i64> [[TMP20]], <i64 48, i64 32>\n ; AVX2-NEXT:    [[TMP3:%.*]] = insertelement <2 x i64> [[TMP20]], i64 [[B_COERCE1:%.*]], i64 1\n ; AVX2-NEXT:    [[TMP4:%.*]] = trunc <2 x i64> [[TMP3]] to <2 x i32>\n-; AVX2-NEXT:    [[B_SROA_3_0_EXTRACT_SHIFT:%.*]] = lshr i64 [[B_COERCE0]], 32\n+; AVX2-NEXT:    [[TMP9:%.*]] = lshr <2 x i64> [[TMP3]], <i64 32, i64 48>\n ; AVX2-NEXT:    [[B_SROA_8_8_EXTRACT_SHIFT:%.*]] = lshr i64 [[B_COERCE1]], 32\n-; AVX2-NEXT:    [[TMP6:%.*]] = insertelement <2 x i64> [[TMP20]], i64 [[A_COERCE0]], i64 0\n ; AVX2-NEXT:    [[TMP7:%.*]] = and <2 x i64> [[TMP6]], splat (i64 65535)\n ; AVX2-NEXT:    [[TMP8:%.*]] = and <2 x i64> [[TMP3]], splat (i64 65535)\n-; AVX2-NEXT:    [[TMP9:%.*]] = insertelement <2 x i32> poison, i32 [[TMP0]], i64 0\n-; AVX2-NEXT:    [[TMP10:%.*]] = insertelement <2 x i32> [[TMP9]], i32 [[TMP1]], i64 1\n+; AVX2-NEXT:    [[TMP19:%.*]] = insertelement <2 x i32> poison, i32 [[TMP1]], i64 0\n+; AVX2-NEXT:    [[TMP10:%.*]] = insertelement <2 x i32> [[TMP19]], i32 [[TMP18]], i64 1\n ; AVX2-NEXT:    [[TMP11:%.*]] = lshr <2 x i32> [[TMP10]], splat (i32 16)\n ; AVX2-NEXT:    [[TMP12:%.*]] = lshr <2 x i32> [[TMP4]], splat (i32 16)\n-; AVX2-NEXT:    [[A_SROA_9_8_EXTRACT_SHIFT:%.*]] = lshr i64 [[A_COERCE1]], 48\n-; AVX2-NEXT:    [[CONV_2:%.*]] = and i64 [[A_SROA_3_0_EXTRACT_SHIFT]], 65535\n-; AVX2-NEXT:    [[B_SROA_9_8_EXTRACT_SHIFT:%.*]] = lshr i64 [[B_COERCE1]], 48\n-; AVX2-NEXT:    [[CONV2_2:%.*]] = and i64 [[B_SROA_3_0_EXTRACT_SHIFT]], 65535\n+; AVX2-NEXT:    [[TMP36:%.*]] = and <2 x i64> [[TMP5]], <i64 65535, i64 -1>\n+; AVX2-NEXT:    [[TMP39:%.*]] = and <2 x i64> [[TMP9]], <i64 65535, i64 -1>\n ; AVX2-NEXT:    [[TMP13:%.*]] = add nuw nsw <2 x i64> [[TMP7]], splat (i64 1)\n ; AVX2-NEXT:    [[TMP14:%.*]] = add nuw nsw <2 x i64> [[TMP13]], [[TMP8]]\n ; AVX2-NEXT:    [[TMP15:%.*]] = lshr <2 x i64> [[TMP14]], splat (i64 1)\n@@ -890,12 +888,8 @@ define { i64, i64 } @avgr_8_u16(i64 %a.coerce0, i64 %a.coerce1, i64 %b.coerce0,\n ; AVX2-NEXT:    [[TMP35:%.*]] = insertelement <2 x i64> poison, i64 [[ADD_3]], i64 0\n ; AVX2-NEXT:    [[TMP25:%.*]] = insertelement <2 x i64> [[TMP35]], i64 [[CONV2_6]], i64 1\n ; AVX2-NEXT:    [[TMP38:%.*]] = add nuw nsw <2 x i64> [[TMP25]], [[TMP37]]\n-; AVX2-NEXT:    [[ADD_7:%.*]] = add nuw nsw i64 [[A_SROA_9_8_EXTRACT_SHIFT]], 1\n-; AVX2-NEXT:    [[ADD_2:%.*]] = add nuw nsw i64 [[CONV_2]], 1\n-; AVX2-NEXT:    [[ADD3_7:%.*]] = add nuw nsw i64 [[ADD_7]], [[B_SROA_9_8_EXTRACT_SHIFT]]\n-; AVX2-NEXT:    [[ADD3_2:%.*]] = add nuw nsw i64 [[ADD_2]], [[CONV2_2]]\n-; AVX2-NEXT:    [[TMP39:%.*]] = insertelement <2 x i64> poison, i64 [[ADD3_2]], i64 0\n-; AVX2-NEXT:    [[TMP40:%.*]] = insertelement <2 x i64> [[TMP39]], i64 [[ADD3_7]], i64 1\n+; AVX2-NEXT:    [[TMP42:%.*]] = add nuw nsw <2 x i64> [[TMP36]], splat (i64 1)\n+; AVX2-NEXT:    [[TMP40:%.*]] = add nuw nsw <2 x i64> [[TMP42]], [[TMP39]]\n ; AVX2-NEXT:    [[TMP41:%.*]] = shl nuw <2 x i64> [[TMP40]], <i64 31, i64 47>\n ; AVX2-NEXT:    [[TMP31:%.*]] = and <2 x i64> [[TMP41]], <i64 281470681743360, i64 -281474976710656>\n ; AVX2-NEXT:    [[TMP32:%.*]] = shl nuw <2 x i64> [[TMP38]], <i64 47, i64 31>\n@@ -917,28 +911,23 @@ define { i64, i64 } @avgr_8_u16(i64 %a.coerce0, i64 %a.coerce1, i64 %b.coerce0,\n ; AVX512-NEXT:    [[TMP0:%.*]] = trunc i64 [[A_COERCE0:%.*]] to i32\n ; AVX512-NEXT:    [[TMP1:%.*]] = insertelement <2 x i64> poison, i64 [[A_COERCE0]], i64 0\n ; AVX512-NEXT:    [[TMP2:%.*]] = insertelement <2 x i64> [[TMP1]], i64 [[B_COERCE1:%.*]], i64 1\n-; AVX512-NEXT:    [[TMP3:%.*]] = lshr <2 x i64> [[TMP2]], <i64 48, i64 32>\n-; AVX512-NEXT:    [[TMP4:%.*]] = trunc i64 [[A_COERCE1:%.*]] to i32\n-; AVX512-NEXT:    [[TMP31:%.*]] = insertelement <2 x i64> poison, i64 [[B_COERCE0:%.*]], i64 0\n-; AVX512-NEXT:    [[TMP32:%.*]] = insertelement <2 x i64> [[TMP31]], i64 [[A_COERCE1]], i64 1\n+; AVX512-NEXT:    [[TMP7:%.*]] = lshr <2 x i64> [[TMP2]], <i64 32, i64 48>\n+; AVX512-NEXT:    [[TMP10:%.*]] = insertelement <2 x i64> [[TMP2]], i64 [[B_COERCE2:%.*]], i64 1\n+; AVX512-NEXT:    [[TMP3:%.*]] = lshr <2 x i64> [[TMP10]], <i64 48, i64 32>\n+; AVX512-NEXT:    [[TMP4:%.*]] = trunc i64 [[B_COERCE1]] to i32\n+; AVX512-NEXT:    [[TMP32:%.*]] = insertelement <2 x i64> [[TMP2]], i64 [[B_COERCE0:%.*]], i64 0\n ; AVX512-NEXT:    [[TMP49:%.*]] = lshr <2 x i64> [[TMP32]], <i64 48, i64 32>\n-; AVX512-NEXT:    [[TMP5:%.*]] = insertelement <2 x i64> [[TMP2]], i64 [[B_COERCE0]], i64 0\n+; AVX512-NEXT:    [[TMP5:%.*]] = insertelement <2 x i64> [[TMP10]], i64 [[B_COERCE0]], i64 0\n ; AVX512-NEXT:    [[TMP6:%.*]] = trunc <2 x i64> [[TMP5]] to <2 x i32>\n-; AVX512-NEXT:    [[TMP7:%.*]] = insertelement <2 x i64> [[TMP32]], i64 [[A_COERCE0]], i64 0\n-; AVX512-NEXT:    [[TMP8:%.*]] = and <2 x i64> [[TMP7]], splat (i64 65535)\n+; AVX512-NEXT:    [[TMP14:%.*]] = lshr <2 x i64> [[TMP5]], <i64 32, i64 48>\n+; AVX512-NEXT:    [[TMP8:%.*]] = and <2 x i64> [[TMP2]], splat (i64 65535)\n ; AVX512-NEXT:    [[TMP9:%.*]] = and <2 x i64> [[TMP5]], splat (i64 65535)\n-; AVX512-NEXT:    [[TMP10:%.*]] = lshr <2 x i64> [[TMP7]], <i64 32, i64 0>\n ; AVX512-NEXT:    [[TMP11:%.*]] = insertelement <2 x i32> poison, i32 [[TMP0]], i64 0\n ; AVX512-NEXT:    [[TMP12:%.*]] = insertelement <2 x i32> [[TMP11]], i32 [[TMP4]], i64 1\n ; AVX512-NEXT:    [[TMP13:%.*]] = lshr <2 x i32> [[TMP12]], splat (i32 16)\n-; AVX512-NEXT:    [[TMP14:%.*]] = lshr <2 x i64> [[TMP5]], <i64 32, i64 0>\n ; AVX512-NEXT:    [[TMP15:%.*]] = lshr <2 x i32> [[TMP6]], splat (i32 16)\n-; AVX512-NEXT:    [[TMP16:%.*]] = and <2 x i64> [[TMP10]], <i64 65535, i64 poison>\n-; AVX512-NEXT:    [[TMP17:%.*]] = lshr <2 x i64> [[TMP10]], <i64 65535, i64 48>\n-; AVX512-NEXT:    [[TMP18:%.*]] = shufflevector <2 x i64> [[TMP16]], <2 x i64> [[TMP17]], <2 x i32> <i32 0, i32 3>\n-; AVX512-NEXT:    [[TMP19:%.*]] = and <2 x i64> [[TMP14]], <i64 65535, i64 poison>\n-; AVX512-NEXT:    [[TMP20:%.*]] = lshr <2 x i64> [[TMP14]], <i64 65535, i64 48>\n-; AVX512-NEXT:    [[TMP21:%.*]] = shufflevector <2 x i64> [[TMP19]], <2 x i64> [[TMP20]], <2 x i32> <i32 0, i32 3>\n+; AVX512-NEXT:    [[TMP18:%.*]] = and <2 x i64> [[TMP7]], <i64 65535, i64 -1>\n+; AVX512-NEXT:    [[TMP21:%.*]] = and <2 x i64> [[TMP14]], <i64 65535, i64 -1>\n ; AVX512-NEXT:    [[TMP22:%.*]] = add nuw nsw <2 x i64> [[TMP8]], splat (i64 1)\n ; AVX512-NEXT:    [[TMP23:%.*]] = add nuw nsw <2 x i64> [[TMP22]], [[TMP9]]\n ; AVX512-NEXT:    [[TMP24:%.*]] = lshr <2 x i64> [[TMP23]], splat (i64 1)\ndiff --git a/llvm/test/Transforms/SLPVectorizer/X86/complex-fma-combine.ll b/llvm/test/Transforms/SLPVectorizer/X86/complex-fma-combine.ll\nindex 5c40ea7d79e89..9cc139e8a02a5 100644\n--- a/llvm/test/Transforms/SLPVectorizer/X86/complex-fma-combine.ll\n+++ b/llvm/test/Transforms/SLPVectorizer/X86/complex-fma-combine.ll\n@@ -6,13 +6,9 @@ define <2 x float> @fma_f32(ptr %A, float %B) {\n ; CHECK-SAME: ptr [[A:%.*]], float [[B:%.*]]) #[[ATTR0:[0-9]+]] {\n ; CHECK-NEXT:  [[ENTRY:.*:]]\n ; CHECK-NEXT:    [[TMP0:%.*]] = load <2 x float>, ptr [[A]], align 4\n-; CHECK-NEXT:    [[RETVAL_SROA_0_0_VEC_EXTRACT_I:%.*]] = extractelement <2 x float> [[TMP0]], i64 0\n-; CHECK-NEXT:    [[RETVAL_SROA_0_4_VEC_EXTRACT_I:%.*]] = extractelement <2 x float> [[TMP0]], i64 1\n-; CHECK-NEXT:    [[MUL_RL_I_I:%.*]] = fmul float [[RETVAL_SROA_0_0_VEC_EXTRACT_I]], 2.000000e+00\n-; CHECK-NEXT:    [[MUL_IL_I_I:%.*]] = fmul float [[RETVAL_SROA_0_4_VEC_EXTRACT_I]], 2.000000e+00\n-; CHECK-NEXT:    [[ADD_R_I_I:%.*]] = fadd float [[B]], [[MUL_RL_I_I]]\n-; CHECK-NEXT:    [[TMP1:%.*]] = insertelement <2 x float> poison, float [[ADD_R_I_I]], i64 0\n-; CHECK-NEXT:    [[RETVAL_SROA_0_0_VEC_INSERT_I6:%.*]] = insertelement <2 x float> [[TMP1]], float [[MUL_IL_I_I]], i64 1\n+; CHECK-NEXT:    [[TMP1:%.*]] = fmul <2 x float> [[TMP0]], splat (float 2.000000e+00)\n+; CHECK-NEXT:    [[TMP2:%.*]] = insertelement <2 x float> <float poison, float -0.000000e+00>, float [[B]], i32 0\n+; CHECK-NEXT:    [[RETVAL_SROA_0_0_VEC_INSERT_I6:%.*]] = fadd <2 x float> [[TMP2]], [[TMP1]]\n ; CHECK-NEXT:    ret <2 x float> [[RETVAL_SROA_0_0_VEC_INSERT_I6]]\n ;\n entry:\ndiff --git a/llvm/test/Transforms/SLPVectorizer/X86/gathered-loads-non-full-reg.ll b/llvm/test/Transforms/SLPVectorizer/X86/gathered-loads-non-full-reg.ll\nindex 74a4fb3ff2b00..6416d5a6062c7 100644\n--- a/llvm/test/Transforms/SLPVectorizer/X86/gathered-loads-non-full-reg.ll\n+++ b/llvm/test/Transforms/SLPVectorizer/X86/gathered-loads-non-full-reg.ll\n@@ -11,7 +11,9 @@ define void @test(ptr noalias %0) {\n ; CHECK-NEXT:    [[TMP2:%.*]] = getelementptr i8, ptr [[TMP0]], i64 32\n ; CHECK-NEXT:    [[TMP3:%.*]] = getelementptr i8, ptr [[TMP0]], i64 128\n ; CHECK-NEXT:    [[TMP4:%.*]] = getelementptr i8, ptr [[TMP0]], i64 200\n+; CHECK-NEXT:    [[TMP5:%.*]] = getelementptr i8, ptr [[TMP0]], i64 208\n ; CHECK-NEXT:    [[TMP6:%.*]] = getelementptr i8, ptr [[TMP0]], i64 232\n+; CHECK-NEXT:    [[TMP7:%.*]] = getelementptr i8, ptr [[TMP0]], i64 288\n ; CHECK-NEXT:    [[TMP8:%.*]] = getelementptr i8, ptr [[TMP0]], i64 320\n ; CHECK-NEXT:    [[TMP9:%.*]] = getelementptr i8, ptr [[TMP0]], i64 304\n ; CHECK-NEXT:    [[TMP10:%.*]] = getelementptr i8, ptr [[TMP0]], i64 424\n@@ -23,47 +25,46 @@ define void @test(ptr noalias %0) {\n ; CHECK-NEXT:    [[TMP28:%.*]] = load double, ptr [[TMP2]], align 8\n ; CHECK-NEXT:    [[TMP29:%.*]] = fadd double [[TMP28]], [[TMP27]]\n ; CHECK-NEXT:    [[DOTNEG969:%.*]] = load double, ptr [[TMP3]], align 8\n+; CHECK-NEXT:    [[TMP19:%.*]] = load double, ptr [[TMP4]], align 8\n+; CHECK-NEXT:    [[TMP24:%.*]] = load double, ptr [[TMP5]], align 8\n+; CHECK-NEXT:    [[TMP26:%.*]] = load double, ptr [[TMP6]], align 8\n+; CHECK-NEXT:    [[TMP22:%.*]] = fadd double [[TMP26]], [[TMP24]]\n+; CHECK-NEXT:    [[TMP23:%.*]] = load double, ptr [[TMP7]], align 8\n ; CHECK-NEXT:    [[TMP17:%.*]] = load double, ptr [[TMP8]], align 8\n ; CHECK-NEXT:    [[TMP25:%.*]] = load double, ptr [[TMP9]], align 8\n ; CHECK-NEXT:    [[TMP31:%.*]] = load double, ptr [[TMP10]], align 8\n ; CHECK-NEXT:    [[TMP21:%.*]] = load double, ptr [[TMP11]], align 8\n ; CHECK-NEXT:    [[TMP20:%.*]] = load double, ptr [[TMP12]], align 8\n ; CHECK-NEXT:    [[TMP36:%.*]] = fadd double [[TMP20]], [[TMP21]]\n-; CHECK-NEXT:    [[TMP32:%.*]] = fsub double 0.000000e+00, [[TMP25]]\n-; CHECK-NEXT:    [[TMP33:%.*]] = fmul double [[TMP32]], 0.000000e+00\n-; CHECK-NEXT:    [[TMP34:%.*]] = fadd double [[TMP33]], 0.000000e+00\n+; CHECK-NEXT:    [[TMP34:%.*]] = fmul double [[TMP22]], [[DOTNEG969]]\n ; CHECK-NEXT:    [[TMP35:%.*]] = fmul double [[TMP34]], 0.000000e+00\n-; CHECK-NEXT:    [[TMP37:%.*]] = fmul double [[TMP36]], [[TMP31]]\n+; CHECK-NEXT:    [[TMP32:%.*]] = fsub double [[TMP29]], [[TMP19]]\n+; CHECK-NEXT:    [[TMP37:%.*]] = fmul double [[TMP32]], [[TMP23]]\n ; CHECK-NEXT:    [[TMP38:%.*]] = fmul double [[TMP37]], 0.000000e+00\n-; CHECK-NEXT:    [[TMP42:%.*]] = fadd double [[TMP38]], 0.000000e+00\n ; CHECK-NEXT:    [[TMP30:%.*]] = load double, ptr [[TMP0]], align 8\n ; CHECK-NEXT:    [[TMP40:%.*]] = load double, ptr [[TMP13]], align 8\n+; CHECK-NEXT:    [[TMP47:%.*]] = fmul double [[TMP40]], [[TMP35]]\n ; CHECK-NEXT:    [[TMP60:%.*]] = load double, ptr [[TMP14]], align 8\n-; CHECK-NEXT:    [[TMP41:%.*]] = fmul double [[TMP35]], 0.000000e+00\n-; CHECK-NEXT:    [[TMP43:%.*]] = fmul double [[TMP60]], [[TMP42]]\n-; CHECK-NEXT:    store double [[TMP41]], ptr getelementptr inbounds (i8, ptr @solid_, i64 384), align 8\n-; CHECK-NEXT:    store double [[TMP43]], ptr getelementptr inbounds (i8, ptr @solid_, i64 392), align 8\n-; CHECK-NEXT:    [[TMP44:%.*]] = load <2 x double>, ptr [[TMP4]], align 8\n-; CHECK-NEXT:    [[TMP46:%.*]] = call <8 x double> @llvm.masked.load.v8f64.p0(ptr align 8 [[TMP6]], <8 x i1> <i1 true, i1 false, i1 false, i1 false, i1 false, i1 false, i1 false, i1 true>, <8 x double> poison)\n-; CHECK-NEXT:    [[TMP50:%.*]] = shufflevector <8 x double> [[TMP46]], <8 x double> poison, <2 x i32> <i32 7, i32 0>\n-; CHECK-NEXT:    [[TMP39:%.*]] = insertelement <2 x double> [[TMP50]], double [[TMP29]], i32 0\n-; CHECK-NEXT:    [[TMP55:%.*]] = fsub <2 x double> [[TMP39]], [[TMP44]]\n-; CHECK-NEXT:    [[TMP57:%.*]] = fadd <2 x double> [[TMP39]], [[TMP44]]\n-; CHECK-NEXT:    [[TMP62:%.*]] = shufflevector <2 x double> [[TMP55]], <2 x double> [[TMP57]], <2 x i32> <i32 0, i32 3>\n-; CHECK-NEXT:    [[TMP51:%.*]] = insertelement <2 x double> [[TMP50]], double [[DOTNEG969]], i32 1\n-; CHECK-NEXT:    [[TMP52:%.*]] = fmul <2 x double> [[TMP62]], [[TMP51]]\n-; CHECK-NEXT:    [[TMP45:%.*]] = fmul <2 x double> [[TMP52]], zeroinitializer\n-; CHECK-NEXT:    [[TMP63:%.*]] = insertelement <2 x double> poison, double [[TMP60]], i32 0\n-; CHECK-NEXT:    [[TMP56:%.*]] = insertelement <2 x double> [[TMP63]], double [[TMP40]], i32 1\n+; CHECK-NEXT:    [[TMP39:%.*]] = fadd double [[TMP47]], 0.000000e+00\n+; CHECK-NEXT:    [[TMP61:%.*]] = fmul double [[TMP60]], [[TMP38]]\n+; C...\n[truncated]\n\n``````````\n\n</details>\n"
    }
  ],
  "knowledge_cutoff": "2026-05-17T17:12:25Z",
  "patch_location_lineno": {
    "llvm/lib/Transforms/Vectorize/SLPVectorizer.cpp": [
      [
        11739,
        11744
      ]
    ],
    "llvm/test/Transforms/PhaseOrdering/X86/avg.ll": [
      [
        42,
        54
      ],
      [
        144,
        156
      ],
      [
        747,
        757
      ],
      [
        810,
        820
      ],
      [
        856,
        883
      ],
      [
        890,
        901
      ],
      [
        917,
        944
      ]
    ],
    "llvm/test/Transforms/SLPVectorizer/X86/complex-fma-combine.ll": [
      [
        6,
        18
      ]
    ],
    "llvm/test/Transforms/SLPVectorizer/X86/gathered-loads-non-full-reg.ll": [
      [
        11,
        17
      ],
      [
        23,
        69
      ]
    ],
    "llvm/test/Transforms/SLPVectorizer/buildvector-nodes-dependency.ll": [
      [
        10,
        25
      ],
      [
        44,
        59
      ]
    ]
  },
  "patch_location_funcname": {
    "llvm/lib/Transforms/Vectorize/SLPVectorizer.cpp": [
      "findAndSetMainInstruction"
    ]
  }
}
